supervaizer/__init__.py
supervaizer/__version__.py
supervaizer/account.py
supervaizer/account_service.py
supervaizer/agent.py
supervaizer/case.py
supervaizer/cli.py
supervaizer/common.py
supervaizer/event.py
supervaizer/instructions.py
supervaizer/job.py
supervaizer/job_service.py
supervaizer/lifecycle.py
supervaizer/parameter.py
supervaizer/routes.py
supervaizer/server.py
supervaizer/server_utils.py
supervaizer/storage.py
supervaizer/telemetry.py
supervaizer/admin/routes.py
supervaizer/admin/static/favicon.ico
supervaizer/admin/static/js/job-start-form.js
supervaizer/admin/templates/agent_detail.html
supervaizer/admin/templates/agents.html
supervaizer/admin/templates/agents_grid.html
supervaizer/admin/templates/base.html
supervaizer/admin/templates/case_detail.html
supervaizer/admin/templates/cases_list.html
supervaizer/admin/templates/cases_table.html
supervaizer/admin/templates/console.html
supervaizer/admin/templates/dashboard.html
supervaizer/admin/templates/index.html
supervaizer/admin/templates/job_detail.html
supervaizer/admin/templates/job_start_test.html
supervaizer/admin/templates/jobs_list.html
supervaizer/admin/templates/jobs_table.html
supervaizer/admin/templates/navigation.html
supervaizer/admin/templates/recent_activity.html
supervaizer/admin/templates/server.html
supervaizer/admin/templates/server_status_cards.html
supervaizer/admin/templates/supervaize_instructions.html
supervaizer/deploy/__init__.py
supervaizer/deploy/cli.py
supervaizer/deploy/docker.py
supervaizer/deploy/driver_factory.py
supervaizer/deploy/health.py
supervaizer/deploy/state.py
supervaizer/deploy/utils.py
supervaizer/deploy/commands/__init__.py
supervaizer/deploy/commands/clean.py
supervaizer/deploy/commands/down.py
supervaizer/deploy/commands/local.py
supervaizer/deploy/commands/plan.py
supervaizer/deploy/commands/status.py
supervaizer/deploy/commands/up.py
supervaizer/deploy/drivers/__init__.py
supervaizer/deploy/drivers/aws_app_runner.py
supervaizer/deploy/drivers/base.py
supervaizer-0.10.14.dist-info/METADATA
supervaizer-0.10.14.dist-info/WHEEL
supervaizer-0.10.14.dist-info/entry_points.txt
supervaizer-0.10.14.dist-info/licenses/LICENSE.md
supervaizer-0.10.14.dist-info/RECORD
