Metadata-Version: 2.4
Name: supervaizer
Version: 0.10.14
Summary: Controller system for Supervaize
Project-URL: Homepage, https://supervaize.com
Project-URL: Repository, https://github.com/supervaize/supervaizer
Project-URL: Documentation, https://doc.supervaize.com
Author-email: Alain Prasquier - Supervaize <alain@supervaize.com>
License-Expression: MPL-2.0
License-File: LICENSE.md
Keywords: AI,agent,agentic,controller,supervaize,workflow
Classifier: Development Status :: 4 - Beta
Classifier: Intended Audience :: Developers
Classifier: License :: OSI Approved :: Mozilla Public License 2.0 (MPL 2.0)
Classifier: Programming Language :: Python :: 3
Classifier: Programming Language :: Python :: 3.12
Classifier: Programming Language :: Python :: 3.13
Requires-Python: >=3.12
Requires-Dist: art>=6.5
Requires-Dist: cryptography>=46.0.0
Requires-Dist: demjson3>=3.0.0
Requires-Dist: deprecated>=1.3.0
Requires-Dist: fastapi>=0.128.0
Requires-Dist: httpx>=0.28.1
Requires-Dist: jinja2>=3.1.6
Requires-Dist: loguru>=0.7.3
Requires-Dist: orjson>=3.11.5
Requires-Dist: packaging>=25.0
Requires-Dist: psutil>=7.2.0
Requires-Dist: pydantic>=2.12.0
Requires-Dist: python-slugify>=8.0.0
Requires-Dist: pyyaml>=6.0.0
Requires-Dist: rich>=14.3.0
Requires-Dist: shortuuid>=1.0.0
Requires-Dist: sse-starlette>=3.2.0
Requires-Dist: tinydb>=4.8.0
Requires-Dist: typer>=0.21.0
Requires-Dist: uvicorn>=0.40.0
Provides-Extra: deploy
Requires-Dist: boto3>=1.42.30; extra == 'deploy'
Requires-Dist: docker>=7.0.0; extra == 'deploy'
Requires-Dist: google-cloud-artifact-registry>=1.19.0; extra == 'deploy'
Requires-Dist: google-cloud-run>=0.15.0; extra == 'deploy'
Requires-Dist: google-cloud-secret-manager>=2.26.0; extra == 'deploy'
Provides-Extra: dev
Requires-Dist: hatch>=1.16.3; extra == 'dev'
Requires-Dist: jsonschema>=4.26.0; extra == 'dev'
Requires-Dist: mypy>=1.19.1; extra == 'dev'
Requires-Dist: pre-commit>=4.5.1; extra == 'dev'
Requires-Dist: pytest-asyncio>=1.3.0; extra == 'dev'
Requires-Dist: pytest-cov>=7.0.0; extra == 'dev'
Requires-Dist: pytest-mock>=3.15.1; extra == 'dev'
Requires-Dist: pytest-sugar>=1.1.1; extra == 'dev'
Requires-Dist: pytest>=8.5.0; extra == 'dev'
Requires-Dist: respx>=0.22.0; extra == 'dev'
Requires-Dist: ruff>=0.14.14; extra == 'dev'
Requires-Dist: types-deprecated>=1.3.1; extra == 'dev'
Requires-Dist: types-python-slugify>=8.0.2.20240310; extra == 'dev'
